zxkane/cdk_construct_simple_nat/__init__.py
zxkane/cdk_construct_simple_nat/py.typed
zxkane/cdk_construct_simple_nat/_jsii/__init__.py
zxkane/cdk_construct_simple_nat/_jsii/cdk-construct-simple-nat@0.2.742.jsii.tgz
zxkane.cdk_construct_simple_nat-0.2.742.dist-info/LICENSE
zxkane.cdk_construct_simple_nat-0.2.742.dist-info/METADATA
zxkane.cdk_construct_simple_nat-0.2.742.dist-info/WHEEL
zxkane.cdk_construct_simple_nat-0.2.742.dist-info/top_level.txt
zxkane.cdk_construct_simple_nat-0.2.742.dist-info/RECORD
